pytorch_benchmark/__init__.py
pytorch_benchmark/benchmark.py
pytorch_benchmark/format.py
pytorch_benchmark/jetson_power.py
pytorch_benchmark/machine_info.py
pytorch_benchmark-0.3.6.dist-info/LICENSE
pytorch_benchmark-0.3.6.dist-info/METADATA
pytorch_benchmark-0.3.6.dist-info/WHEEL
pytorch_benchmark-0.3.6.dist-info/top_level.txt
pytorch_benchmark-0.3.6.dist-info/RECORD
